.gitignore
.travis.yml
CHANGES.rst
CONTRIBUTORS.rst
MANIFEST.in
README.rst
base.cfg
bootstrap.py
buildout.cfg
checkouts.cfg
jenkins-base.cfg
jenkins.cfg
requirements.txt
setup.py
sources.cfg
travis.cfg
versions.cfg
docs/LICENSE.GPL
docs/LICENSE.txt
src/collective/__init__.py
src/collective.dms.basecontent.egg-info/PKG-INFO
src/collective.dms.basecontent.egg-info/SOURCES.txt
src/collective.dms.basecontent.egg-info/dependency_links.txt
src/collective.dms.basecontent.egg-info/entry_points.txt
src/collective.dms.basecontent.egg-info/namespace_packages.txt
src/collective.dms.basecontent.egg-info/not-zip-safe
src/collective.dms.basecontent.egg-info/requires.txt
src/collective.dms.basecontent.egg-info/top_level.txt
src/collective/dms/__init__.py
src/collective/dms/basecontent/__init__.py
src/collective/dms/basecontent/configure.zcml
src/collective/dms/basecontent/dmsdocument.py
src/collective/dms/basecontent/dmsfile.py
src/collective/dms/basecontent/indexers.py
src/collective/dms/basecontent/permissions.zcml
src/collective/dms/basecontent/related-docs-display.pt
src/collective/dms/basecontent/relateddocs.py
src/collective/dms/basecontent/setuphandlers.py
src/collective/dms/basecontent/source.py
src/collective/dms/basecontent/testing.py
src/collective/dms/basecontent/testing.zcml
src/collective/dms/basecontent/browser/__init__.py
src/collective/dms/basecontent/browser/batch.py
src/collective/dms/basecontent/browser/column.py
src/collective/dms/basecontent/browser/configure.zcml
src/collective/dms/basecontent/browser/listing.py
src/collective/dms/basecontent/browser/table.py
src/collective/dms/basecontent/browser/viewlets.py
src/collective/dms/basecontent/browser/views.py
src/collective/dms/basecontent/browser/static/img/dmsappendixfile_icon.png
src/collective/dms/basecontent/browser/static/img/dmsdocument_icon.png
src/collective/dms/basecontent/browser/static/img/dmsmainfile_icon.png
src/collective/dms/basecontent/browser/static/img/fade_edit.png
src/collective/dms/basecontent/browser/templates/dmsdocument_edit.pt
src/collective/dms/basecontent/browser/templates/dmsdocument_view.pt
src/collective/dms/basecontent/browser/templates/filesviewlet.pt
src/collective/dms/basecontent/browser/templates/versionsviewlet.pt
src/collective/dms/basecontent/browser/templates/versionviewer.pt
src/collective/dms/basecontent/locales/collective.dms.basecontent.pot
src/collective/dms/basecontent/locales/plone.pot
