Metadata-Version: 2.1
Name: collective.dms.basecontent
Version: 1.11
Summary: Base content types for document management system
Home-page: https://github.com/collective/collective.dms.basecontent
Author: Ecreall, Entrouvert, IMIO
Author-email: cedricmessiant@ecreall.com
License: gpl
Download-URL: https://pypi.org/project/collective.dms.basecontent
Keywords: document management system dms viewer
Platform: UNKNOWN
Classifier: Development Status :: 5 - Production/Stable
Classifier: Environment :: Web Environment
Classifier: Framework :: Plone
Classifier: Framework :: Plone :: Addon
Classifier: Framework :: Plone :: 4.2
Classifier: Framework :: Plone :: 4.3
Classifier: License :: OSI Approved :: GNU General Public License v2 (GPLv2)
Classifier: Operating System :: OS Independent
Classifier: Programming Language :: Python
Classifier: Programming Language :: Python :: 2.7
Classifier: Topic :: Software Development :: Libraries :: Python Modules
Provides-Extra: test
